peakutils/__init__.py
peakutils/baseline.py
peakutils/peak.py
peakutils/plot.py
peakutils/prepare.py
PeakUtils-1.3.4.dist-info/LICENSE.txt
PeakUtils-1.3.4.dist-info/METADATA
PeakUtils-1.3.4.dist-info/WHEEL
PeakUtils-1.3.4.dist-info/top_level.txt
PeakUtils-1.3.4.dist-info/RECORD
