Metadata-Version: 2.1
Name: PeakUtils
Version: 1.3.4
Summary: Peak detection utilities for 1D data
Home-page: https://bitbucket.org/lucashnegri/peakutils
Author: Lucas Hermann Negri
Author-email: lucashnegri@gmail.com
License: MIT
Keywords: peak detection search gaussian centroid baseline maximum
Classifier: Development Status :: 5 - Production/Stable
Classifier: License :: OSI Approved :: MIT License
Classifier: Programming Language :: Python
Classifier: Programming Language :: Python :: 3
Classifier: Topic :: Scientific/Engineering
License-File: LICENSE.txt
